[
  {
    "characterName": "New Character Name",
    "playerName": "Player Name",
    "cardPhotoUrl": "",
    "sheetPhotoUrl": "",
    "sources": [
      {
        "_id": "srd",
        "name": "System Reference Document"
      },
      {
        "_id": "exp1",
        "name": "Experimental Source 1"
      },
      {
        "_id": "exp2",
        "name": "Experimental Source 2"
      }
    ],
    "classId": {
      "ref": "class",
      "name": "Barbarian",
      "source": {
        "_id": "srd",
        "name": "System Reference Document"
      }
    },
    "subclass": "Berserker",
    "raceId": {
      "ref": "race",
      "name": "Human",
      "source": {
        "_id": "srd",
        "name": "System Reference Document"
      }
    },
    "size": "small",
    "backgroundId": {
      "ref": "background",
      "name": "Space Pirate",
      "source": {
        "_id": "exp2",
        "name": "Experimental Source 2"
      }
    },
    "level": 1,
    "abilities": {
      "constitution": {
        "label": "constitution",
        "score": 8,
        "upByOne": false,
        "upByTwo": false
      },
      "strength": {
        "label": "strength",
        "score": 8,
        "upByOne": false,
        "upByTwo": false
      },
      "wisdom": {
        "label": "wisdom",
        "score": 8,
        "upByOne": false,
        "upByTwo": false
      },
      "charisma": {
        "label": "charisma",
        "score": 8,
        "upByOne": false,
        "upByTwo": false
      },
      "dexterity": {
        "label": "dexterity",
        "score": 8,
        "upByOne": false,
        "upByTwo": false
      },
      "intelligence": {
        "label": "intelligence",
        "score": 8,
        "upByOne": false,
        "upByTwo": false
      }
    },
    "skills": [
      "insight",
      "perception",
      "athletics",
      "religion",
      "medicine",
      "animal_handling"
    ],
    "tools": [
      {
        "item": {
          "ref": "tool",
          "name": "Drill",
          "source": {
            "_id": "exp1",
            "name": "Experimental Source 1"
          }
        },
        "from": "background"
      },
      {
        "item": {
          "ref": "tool",
          "name": "Testing tool 3",
          "source": {
            "_id": "exp2",
            "name": "Experimental Source 2"
          }
        },
        "from": "background"
      },
      {
        "item": {
          "ref": "tool",
          "name": "Painter's supplies",
          "source": {
            "_id": "srd",
            "name": "System Reference Document"
          }
        },
        "from": "background"
      }
    ],
    "languages": [
      {
        "item": {
          "ref": "language",
          "name": "French",
          "source": {
            "_id": "exp1",
            "name": "Experimental Source 1"
          }
        },
        "from": "background"
      },
      {
        "item": {
          "ref": "language",
          "name": "Dutch",
          "source": {
            "_id": "exp1",
            "name": "Experimental Source 1"
          }
        },
        "from": "background"
      },
      {
        "item": {
          "ref": "language",
          "name": "Draconic",
          "source": {
            "_id": "srd",
            "name": "System Reference Document"
          }
        },
        "from": "background"
      },
      {
        "item": {
          "ref": "language",
          "name": "Common",
          "source": {
            "_id": "srd",
            "name": "System Reference Document"
          }
        },
        "from": "race"
      }
    ],
    "armor": {
      "ref": "armor",
      "name": "Bastion of Testing",
      "source": {
        "_id": "exp2",
        "name": "Experimental Source 2"
      }
    },
    "weapons": [
      {
        "ref": "weapon",
        "name": "Anklebiter",
        "source": {
          "_id": "exp1",
          "name": "Experimental Source 1"
        }
      },
      {
        "ref": "weapon",
        "name": "Crossbow of Annoyance",
        "source": {
          "_id": "exp1",
          "name": "Experimental Source 1"
        }
      },
      {
        "ref": "weapon",
        "name": "Sword of Flames",
        "source": {
          "_id": "exp2",
          "name": "Experimental Source 2"
        }
      },
      {
        "ref": "weapon",
        "name": "Club",
        "source": {
          "_id": "srd",
          "name": "System Reference Document"
        }
      },
      {
        "ref": "weapon",
        "name": "Dagger",
        "source": {
          "_id": "srd",
          "name": "System Reference Document"
        }
      }
    ],
    "spells": [],
    "_class": "cz.cvut.fit.anteater.model.entity.Character"
  }
]